ai_forge/__init__.py
ai_forge/exceptions.py
ai_forge/py.typed
ai_forge/builtin_templates/.gitkeep
ai_forge/builtin_templates/__init__.py
ai_forge/builtin_templates/starter/README.md
ai_forge/builtin_templates/starter/__init__.py
ai_forge/builtin_templates/starter/template.yaml
ai_forge/builtin_templates/starter/files/CLAUDE.md.j2
ai_forge/builtin_templates/starter/files/format-on-save.sh.j2
ai_forge/builtin_templates/starter/files/settings.json.j2
ai_forge/builtin_templates/starter/validation/__init__.py
ai_forge/builtin_templates/starter/validation/files.py
ai_forge/builtin_templates/starter/validation/variables.py
ai_forge/cli/__init__.py
ai_forge/cli/console.py
ai_forge/cli/errors.py
ai_forge/cli/main.py
ai_forge/cli/commands/__init__.py
ai_forge/cli/commands/init.py
ai_forge/core/__init__.py
ai_forge/core/config.py
ai_forge/core/loader.py
ai_forge/generators/__init__.py
ai_forge/generators/agents.py
ai_forge/generators/base.py
ai_forge/generators/claude_md.py
ai_forge/generators/hooks.py
ai_forge/generators/mcp.py
ai_forge/generators/settings.py
ai_forge/templates/__init__.py
ai_forge/templates/base.py
ai_forge/templates/loader.py
ai_forge/templates/manifest.py
ai_forge/templates/renderer.py
ai_forge/templates/security.py
ai_forge/utils/__init__.py
ai_forge/utils/filesystem.py
ai_forge/utils/security.py
ai_forge_collective-1.1.0.dist-info/METADATA
ai_forge_collective-1.1.0.dist-info/WHEEL
ai_forge_collective-1.1.0.dist-info/entry_points.txt
ai_forge_collective-1.1.0.dist-info/licenses/LICENSE
ai_forge_collective-1.1.0.dist-info/RECORD
