Metadata-Version: 2.4
Name: ai-forge-collective
Version: 1.1.0
Summary: A Python tool for programmatically building and validating Claude workflow instructions for AI Forge
Project-URL: Home, https://github.com/ddlaws0n/ai-forge
Project-URL: Documentation, https://github.com/ddlaws0n/ai-forge/blob/main/README.md
Project-URL: Issues, https://github.com/ddlaws0n/ai-forge/issues
Author-email: Marco Cricchio <mcricchio@gmail.com>, David D Lawson <david@lawson.dev>
License: MIT
License-File: LICENSE
Classifier: Development Status :: 3 - Alpha
Classifier: Intended Audience :: Developers
Classifier: License :: OSI Approved :: MIT License
Classifier: Programming Language :: Python :: 3.12
Classifier: Topic :: Software Development :: Libraries :: Python Modules
Requires-Python: >=3.12
Requires-Dist: click>=8.2.1
Requires-Dist: jinja2>=3.1.6
Requires-Dist: pydantic>=2.11.7
Requires-Dist: pyyaml>=6.0.2
Requires-Dist: rich>=14.0.0
